tolha/__init__.py
tolha/models/call.py
tolha/models/invoice.py
tolha/models/response.py
tolha/myais.py
tolha-0.2.0.dist-info/LICENSE.md
tolha-0.2.0.dist-info/WHEEL
tolha-0.2.0.dist-info/METADATA
tolha-0.2.0.dist-info/RECORD
