Metadata-Version: 2.1
Name: tolha
Version: 0.2.0
Summary: Unofficial Library to access your my telco data
Home-page: https://github.com/CircleOnCircles/tolha
License: ISC
Author: Nutchanon Ninyawee
Author-email: nutchanon@codustry.com
Requires-Python: >=3.8,<4.0
Classifier: License :: OSI Approved
Classifier: Programming Language :: Python :: 3
Classifier: Programming Language :: Python :: 3.10
Classifier: Programming Language :: Python :: 3.8
Classifier: Programming Language :: Python :: 3.9
Requires-Dist: fastapi-utils (>=0.2.1,<0.3.0)
Requires-Dist: loguru (>=0.5.3,<0.6.0)
Requires-Dist: playwright (>=0.142.3,<0.143.0)
Requires-Dist: pydantic[dotenv] (>=1.8.2,<2.0.0)
Requires-Dist: python-decouple (>=3.3,<4.0)
Project-URL: Repository, https://github.com/CircleOnCircles/tolha
